{
	"title": "Karibik za rozumné peníze: kam a za kolik",
	"slug": "top-5-karibik-budget",
	"excerpt": "Karibik zní jako dovolená pro boháče. Ale nemusí to tak být. Dominikánská republika vás překvapí cenami, Portoriko americkým komfortem a i na drahých Panensk...",
	"articleType": "list",
	"contentLang": "cs",
	"tags": ["Karibik", "budget", "pláže", "tropické destinace"],
	"publish": true,
	"readingTime": 4,
	"content": [
		{
			"type": "paragraph",
			"children": [
				{
					"type": "text",
					"text": "Karibik zní jako dovolená pro boháče. Ale nemusí to tak být. Dominikánská republika vás překvapí cenami, Portoriko americkým komfortem a i na drahých Panenských ostrovech se dá přežít. Tady jsou tipy na Karibik s rozumem."
				}
			]
		},
		{
			"type": "heading",
			"level": 3,
			"children": [
				{
					"type": "text",
					"text": "1. Dominikánská republika"
				}
			]
		},
		{
			"type": "paragraph",
			"children": [
				{
					"type": "text",
					"text": "Země plná kokosových palem, krásných pláží s průzračnou vodou Karibského moře, vysokých hor, přírody a dobré nálady, ale také turistů, dotěrných prodejců a odpadků."
				}
			]
		},
		{
			"type": "list",
			"format": "unordered",
			"children": [
				{
					"type": "list-item",
					"children": [
						{
							"type": "text",
							"text": "💰 Budget: od 805 Kč/den (střední: 1840 Kč/den)"
						}
					]
				},
				{
					"type": "list-item",
					"children": [
						{
							"type": "text",
							"text": "📅 Nejlepší doba: prosinec až duben"
						}
					]
				},
				{
					"type": "list-item",
					"children": [
						{
							"type": "text",
							"text": "🛂 Víza: Czech citizens: tourist card on arrival"
						}
					]
				}
			]
		},
		{
			"type": "paragraph",
			"children": [
				{
					"type": "text",
					"text": "→ "
				},
				{
					"type": "link",
					"url": "/destinations/guide/pruvodce-dominikanska-republika",
					"children": [
						{
							"type": "text",
							"text": "Celý průvodce: Dominikánská republika"
						}
					]
				}
			]
		},
		{
			"type": "heading",
			"level": 3,
			"children": [
				{
					"type": "text",
					"text": "2. Portoriko"
				}
			]
		},
		{
			"type": "paragraph",
			"children": [
				{
					"type": "text",
					"text": "Portoriko je krásným a poněkud odlišným ostrovem Karibiku nacházejícím se nedaleko Dominikánské republiky."
				}
			]
		},
		{
			"type": "list",
			"format": "unordered",
			"children": [
				{
					"type": "list-item",
					"children": [
						{
							"type": "text",
							"text": "💰 Budget: od 1035 Kč/den (střední: 2070 Kč/den)"
						}
					]
				},
				{
					"type": "list-item",
					"children": [
						{
							"type": "text",
							"text": "📅 Nejlepší doba: prosinec až duben"
						}
					]
				},
				{
					"type": "list-item",
					"children": [
						{
							"type": "text",
							"text": "🛂 Víza: EU citizens: visa-free (US territory)"
						}
					]
				}
			]
		},
		{
			"type": "paragraph",
			"children": [
				{
					"type": "text",
					"text": "→ "
				},
				{
					"type": "link",
					"url": "/destinations/guide/pruvodce-portoriko",
					"children": [
						{
							"type": "text",
							"text": "Celý průvodce: Portoriko"
						}
					]
				}
			]
		},
		{
			"type": "heading",
			"level": 3,
			"children": [
				{
					"type": "text",
					"text": "3. Britské Panenské Ostrovy"
				}
			]
		},
		{
			"type": "paragraph",
			"children": [
				{
					"type": "text",
					"text": "Britské Panenské ostrovy jsou takovým malým zapomenutým tropickým rájem Karibiku."
				}
			]
		},
		{
			"type": "list",
			"format": "unordered",
			"children": [
				{
					"type": "list-item",
					"children": [
						{
							"type": "text",
							"text": "💰 Budget: od 2760 Kč/den (střední: 5060 Kč/den)"
						}
					]
				},
				{
					"type": "list-item",
					"children": [
						{
							"type": "text",
							"text": "📅 Nejlepší doba: prosinec až duben"
						}
					]
				},
				{
					"type": "list-item",
					"children": [
						{
							"type": "text",
							"text": "🛂 Víza: Czech citizens: visa required or via cruise"
						}
					]
				}
			]
		},
		{
			"type": "paragraph",
			"children": [
				{
					"type": "text",
					"text": "→ "
				},
				{
					"type": "link",
					"url": "/destinations/guide/pruvodce-britske-panenske-ostrovy",
					"children": [
						{
							"type": "text",
							"text": "Celý průvodce: Britské Panenské Ostrovy"
						}
					]
				}
			]
		},
		{
			"type": "heading",
			"level": 3,
			"children": [
				{
					"type": "text",
					"text": "4. Dominikána jih (Santo Domingo, Boca Chica)"
				}
			]
		},
		{
			"type": "paragraph",
			"children": [
				{
					"type": "text",
					"text": "Santo Domingo Santo domingo je hlavním městem Dominikánské republiky. Z cestovatelského hlediska je to město velmi zajímavé."
				}
			]
		},
		{
			"type": "list",
			"format": "unordered",
			"children": [
				{
					"type": "list-item",
					"children": [
						{
							"type": "text",
							"text": "💰 Budget: od 805 Kč/den (střední: 1840 Kč/den)"
						}
					]
				},
				{
					"type": "list-item",
					"children": [
						{
							"type": "text",
							"text": "📅 Nejlepší doba: prosinec až duben"
						}
					]
				},
				{
					"type": "list-item",
					"children": [
						{
							"type": "text",
							"text": "🛂 Víza: Czech citizens: tourist card on arrival"
						}
					]
				}
			]
		},
		{
			"type": "paragraph",
			"children": [
				{
					"type": "text",
					"text": "→ "
				},
				{
					"type": "link",
					"url": "/destinations/guide/pruvodce-dominikana-jih-santo-domingo-boca-chica",
					"children": [
						{
							"type": "text",
							"text": "Celý průvodce: Dominikána jih (Santo Domingo, Boca Chica)"
						}
					]
				}
			]
		},
		{
			"type": "heading",
			"level": 3,
			"children": [
				{
					"type": "text",
					"text": "5. Dominikána jihovýchod (Bayahibe, Dominicus a Saona)"
				}
			]
		},
		{
			"type": "paragraph",
			"children": [
				{
					"type": "text",
					"text": "Jihovýchod \n (Bayahibe, Dominicus a Saona) Tato oblast je jedna z nejhezčích plážových oblastí představující téměř tropický ráj, ale také bohužel jedna z nejturističtějších a nejdražších oblastí."
				}
			]
		},
		{
			"type": "list",
			"format": "unordered",
			"children": [
				{
					"type": "list-item",
					"children": [
						{
							"type": "text",
							"text": "💰 Budget: od 805 Kč/den (střední: 1840 Kč/den)"
						}
					]
				},
				{
					"type": "list-item",
					"children": [
						{
							"type": "text",
							"text": "📅 Nejlepší doba: prosinec až duben"
						}
					]
				},
				{
					"type": "list-item",
					"children": [
						{
							"type": "text",
							"text": "🛂 Víza: Czech citizens: tourist card on arrival"
						}
					]
				}
			]
		},
		{
			"type": "paragraph",
			"children": [
				{
					"type": "text",
					"text": "→ "
				},
				{
					"type": "link",
					"url": "/destinations/guide/pruvodce-dominikana-jihovychod-bayahibe-dominicus-a-saona",
					"children": [
						{
							"type": "text",
							"text": "Celý průvodce: Dominikána jihovýchod (Bayahibe, Dominicus a Saona)"
						}
					]
				}
			]
		},
		{
			"type": "heading",
			"level": 2,
			"children": [
				{
					"type": "text",
					"text": "✈️ Kam dál?"
				}
			]
		},
		{
			"type": "paragraph",
			"children": [
				{
					"type": "text",
					"text": "Každá z těchto destinací má svůj kompletní průvodce s praktickými tipy na dopravu, jídlo a ubytování. Klikni na destinaci, která tě zaujala, a zjisti víc."
				}
			]
		}
	]
}
